Lab09/DataMemory.v
`timescale 1ns / 1ps

`define SIZE 1024

module DataMemory(ReadData , Address , WriteData , MemoryRead , MemoryWrite , Clock);
    input [63:0]      WriteData;
    input [63:0]      Address;
    input             Clock, MemoryRead, MemoryWrite;
    output reg [63:0] ReadData;

    reg [7:0]         memBank [`SIZE-1:0];


    // This task is used to write arbitrary data to the Data Memory by
    // the intialization block.
    task initset;
      input [63:0] addr;
      input [63:0] data;
      begin
     memBank[addr] =  data[63:56] ; // Big-endian for the win...
     memBank[addr+1] =  data[55:48];
     memBank[addr+2] =  data[47:40];
     memBank[addr+3] =  data[39:32];
     memBank[addr+4] =  data[31:24];
     memBank[addr+5] =  data[23:16];
     memBank[addr+6] =  data[15:8];
     memBank[addr+7] =  data[7:0];
      end
    endtask


    initial
    begin
        // preseting some data in the data memory used by test #1

        // Address 0x0 gets 0x1
        initset( 64'h0,  64'h1);  //Counter variable
        initset( 64'h8,  64'ha);  //Part of mask
        initset( 64'h10, 64'h5);  //Other part of mask
        initset( 64'h18, 64'h0ffbea7deadbeeff); //big constant
        initset( 64'h20, 64'h0); //clearing space

        // Add any data you need for your tests here.

    end

    // This always block reads the data memory and places a double word
    // on the ReadData bus.
    always @(posedge Clock)
    begin
        if(MemoryRead)
        begin
            ReadData[63:56] <= #20 memBank[Address];
            ReadData[55:48] <= #20 memBank[Address+1];
            ReadData[47:40] <= #20 memBank[Address+2];
            ReadData[39:32] <= #20 memBank[Address+3];
            ReadData[31:24] <= #20 memBank[Address+4];
            ReadData[23:16] <= #20 memBank[Address+5];
            ReadData[15:8] <= #20 memBank[Address+6];
            ReadData[7:0] <= #20 memBank[Address+7];
        end
    end

    // This always block takes data from the WriteData bus and writes
    // it into the DataMemory.
    always @(posedge Clock)
    begin
        if(MemoryWrite)
        begin
            memBank[Address] <= #20 WriteData[63:56] ;
            memBank[Address+1] <= #20 WriteData[55:48];
            memBank[Address+2] <= #20 WriteData[47:40];
            memBank[Address+3] <= #20 WriteData[39:32];
            memBank[Address+4] <= #20 WriteData[31:24];
            memBank[Address+5] <= #20 WriteData[23:16];
            memBank[Address+6] <= #20 WriteData[15:8];
            memBank[Address+7] <= #20 WriteData[7:0];
            // Could be useful for debugging:
             $display("Writing Address:%h Data:%h",Address, WriteData);
        end
    end
endmodule

Lab09/alu.v
`timescale 1ns / 1ps

`define ALUOP_AND    4'b0000
`define ALUOP_ORR    4'b0001
`define ALUOP_ADD    4'b0010
`define ALUOP_SUB    4'b0110
`define ALUOP_PASSB  4'b0111
`define ALUOP_MOVZ   4'b0011

module alu(
    //output reg [63:0] busW,
    output  [63:0] busW,
    output         zero,
    input      [63:0] busA,
    input      [63:0] busB,
    input      [3:0]  ctrl
);

wire [63:0] subresults [15:0];

assign busW = subresults[ctrl];

// Assign subresults
assign subresults[`ALUOP_AND   ] = busA & busB;
assign subresults[`ALUOP_ORR   ] = busA | busB;
assign subresults[`ALUOP_ADD   ] = busA + busB;
assign subresults[`ALUOP_SUB   ] = busA - busB;
assign subresults[`ALUOP_PASSB ] = busB;
assign subresults[`ALUOP_MOVZ  ] = 1'b0 + busB;


assign zero = (busW ? 1'b0 : 1'b1);


endmodule

Lab09/ImmGeneratorMOV.v
`timescale 1ns / 1ps
module ImmGenerator(Imm64, Imm26, Ctrl);
   output reg [63:0] Imm64;
   input [25:0]  Imm26;
   input [2:0]	 Ctrl;


   wire 	 extBit;

   //assign extBit = (Ctrl ? 1'b0 : Imm32[31]);
   //assign Imm32 = {{32{extBit}}, Imm32};

   
   always@(*)
     begin
        if(Ctrl[2:0] == 3'b000) begin  // I-type
	   Imm64 = {52'b0,Imm26[21:10]};
        end
        if(Ctrl[2:0] == 3'b001)begin // Load/Store
           Imm64 = {{55{Imm26[20]}}, Imm26[20:12]};
	end
	if(Ctrl[2:0] == 3'b010)begin // Uncond. Branch
          Imm64 = {{38{Imm26[25]}}, Imm26[25:0]};
	end
	if(Ctrl[2:0] == 3'b011)begin // Cond. Branch
	  Imm64 = {{45{Imm26[23]}}, Imm26[23:5]};
	end
	if(Ctrl[2:0] == 3'b100)begin// IW-Type 
		if(Imm26[22:21] == 2'b00)begin// LSL 0 
		    Imm64 = {48'b0, Imm26[20:5]};
		end
		if(Imm26[22:21] == 2'b01)begin //LSL 16
 		    Imm64 = {32'b0, Imm26[20:5], 16'b0};		
		end
		if(Imm26[22:21] == 2'b10) begin//LSL 32
		    Imm64 = {16'b0, Imm26[20:5], 32'b0};
		end
		if(Imm26[22:21] == 2'b11)begin//LSL 48
		    Imm64 = {Imm26[20:5], 48'b0};
		end
	  //Imm64 = {Imm26[20:5]<<(Imm26[22:21]*16)};
	end
	if(Ctrl[2:0] == 3'bxxx)begin 
          Imm64 = {64'bx};
        end
	
	
      end
   endmodule

Lab09/registerfile.v
`timescale 1ns / 1ps
module RegisterFile(BusA, BusB, BusW, RA, RB, RW, RegWr, Clk);
	output [63:0] BusA;
	output [63:0] BusB;
	input [63:0] BusW;
	input [4:0] RA;
	input [4:0] RB;
	input [4:0] RW;
	input RegWr;
	input Clk;

	reg [63:0] register [31:0]; // 64, 32-bit registers
	

	always@(negedge Clk) begin
		
	if(RegWr)begin
		if(RW != 31)begin
			register[RW] <= BusW;
		end
	end
	
	end
	assign BusA = (RA==31)?0:register[RA]; // RA indices the registers value on BusA
	assign BusB = (RB==31)?0:register[RB];// RB indices the registers value on BusB
endmodule

Lab09/SingleCycleControlMOV.v
`timescale 1ns / 1ps
`define OPCODE_ANDREG 11'b?0001010???
`define OPCODE_ORRREG 11'b?0101010???
`define OPCODE_ADDREG 11'b?0?01011???
`define OPCODE_SUBREG 11'b?1?01011???

`define OPCODE_ADDIMM 11'b?0?10001???
`define OPCODE_SUBIMM 11'b?1?10001???

`define OPCODE_MOVZ   11'b110100101??

`define OPCODE_B      11'b?00101?????
`define OPCODE_CBZ    11'b?011010????

`define OPCODE_LDUR   11'b??111000010
`define OPCODE_STUR   11'b??111000000

module SingleCycleControl(
    output reg reg2loc,
    output reg alusrc,
    output reg mem2reg,
    output reg regwrite,
    output reg memread,
    output reg memwrite,
    output reg branch,
    output reg uncond_branch,
    output reg [3:0] aluop,
    output reg [2:0] signop,
    input [10:0] opcode
);

always @(opcode)//*)
begin
    casez (opcode)

        /* Add cases here for each instruction your processor supports */
	`OPCODE_ANDREG:
	    begin 
	    reg2loc       <= 1'b0;
            alusrc        <= 1'b0;
            mem2reg       <= 1'b0;
            regwrite      <= 1'b1;
            memread       <= 1'b0;
            memwrite      <= 1'b0;
            branch        <= 1'b0;
            uncond_branch <= 1'b0;
            aluop         <= 4'b0000;
            signop        <= 3'bxxx;
	    end
	`OPCODE_ORRREG:begin 
	    reg2loc       <= 1'b0;
            alusrc        <= 1'b0;
            mem2reg       <= 1'b0;
            regwrite      <= 1'b1;
            memread       <= 1'b0;
            memwrite      <= 1'b0;
            branch        <= 1'b0;
            uncond_branch <= 1'b0;
            aluop         <= 4'b0001;
            signop        <= 3'bxxx;
	    end
	`OPCODE_ADDREG: 
	    begin 
	    reg2loc       <= 1'b0;
            alusrc        <= 1'b0;
            mem2reg       <= 1'b0;
            regwrite      <= 1'b1;
            memread       <= 1'b0;
            memwrite      <= 1'b0;
            branch        <= 1'b0;
            uncond_branch <= 1'b0;
            aluop         <= 4'b0010;
            signop        <= 3'bxxx;
	    end
	`OPCODE_SUBREG: 
	    begin 
	    reg2loc       <= 1'b0;
            alusrc        <= 1'b0;
            mem2reg       <= 1'b0;
            regwrite      <= 1'b1;
            memread       <= 1'b0;
            memwrite      <= 1'b0;
            branch        <= 1'b0;
            uncond_branch <= 1'b0;
            aluop         <= 4'b0110;
            signop        <= 3'bxxx;
 	    end
	`OPCODE_ADDIMM:  
	    begin
	    reg2loc       <= 1'b1;
            alusrc        <= 1'b1;
            mem2reg       <= 1'b0;
            regwrite      <= 1'b1;
            memread       <= 1'b0;
            memwrite      <= 1'b0;
            branch        <= 1'b0;
            uncond_branch <= 1'b0;
            aluop         <= 4'b0010;
            signop        <= 3'b000; 
	    end
	`OPCODE_SUBIMM: 
	    begin 
	    reg2loc       <= 1'b1;
            alusrc        <= 1'b1;
            mem2reg       <= 1'b0;
            regwrite      <= 1'b1;
            memread       <= 1'b0;
            memwrite      <= 1'b0;
            branch        <= 1'b0;
            uncond_branch <= 1'b0;
            aluop         <= 4'b0110;
            signop        <= 3'b000;
	    end
	`OPCODE_MOVZ:   begin 
	    reg2loc       <= 1'b1;
            alusrc        <= 1'b1;
            mem2reg       <= 1'b0;
            regwrite      <= 1'b1;
            memread       <= 1'b0;
            memwrite      <= 1'b0;
            branch        <= 1'b0;
            uncond_branch <= 1'b0;
            aluop         <= 4'b0011;
            signop        <= 3'b100;
	    end
	`OPCODE_B:     
	    begin 
	    reg2loc       <= 1'bx;
            alusrc        <= 1'bx;
            mem2reg       <= 1'bx;
            regwrite      <= 1'b0;
            memread       <= 1'b0;
            memwrite      <= 1'b0;
            branch        <= 1'bx;
            uncond_branch <= 1'b1;
            aluop         <= 4'bxxxx;
            signop        <= 3'b010;
	    end
	`OPCODE_CBZ:    
	    begin 
	    reg2loc       <= 1'b1;
            alusrc        <= 1'b0;
            mem2reg       <= 1'bx;
            regwrite      <= 1'b0;
            memread       <= 1'b0;
            memwrite      <= 1'b0;
            branch        <= 1'b1;
            uncond_branch <= 1'b0;
            aluop         <= 4'b0111;
            signop        <= 3'b011;
	    end
	`OPCODE_LDUR:   
 	    begin 
	    reg2loc       <= 1'bx;
            alusrc        <= 1'b1;
            mem2reg       <= 1'b1;
            regwrite      <= 1'b1;
            memread       <= 1'b1;
            memwrite      <= 1'b0;
            branch        <= 1'b0;
            uncond_branch <= 1'b0;
            aluop         <= 4'b0010;
            signop        <= 3'b001;
	    end
	`OPCODE_STUR:  
	    begin 
	    reg2loc       <= 1'b1;
            alusrc        <= 1'b1;
            mem2reg       <= 1'bx;
            regwrite      <= 1'b0;
            memread       <= 1'b0;
            memwrite      <= 1'b1;
            branch        <= 1'b0;
            uncond_branch <= 1'b0;
            aluop         <= 4'b0010;
            signop        <= 3'b001;
	    end

        default:
        begin
            reg2loc       <= 1'bx;
            alusrc        <= 1'bx;
            mem2reg       <= 1'bx;
            regwrite      <= 1'b0;
            memread       <= 1'b0;
            memwrite      <= 1'b0;
            branch        <= 1'b0;
            uncond_branch <= 1'b0;
            aluop         <= 4'bxxxx;
            signop        <= 3'bxxx;
        end
    endcase
end

endmodule

Lab09/InstructionMemory.v
`timescale 1ns / 1ps
/*
 * Module: InstructionMemory
 *
 * Implements read-only instruction memory
 *
 */
module InstructionMemory(Data, Address);
    output [31:0] Data;
    input [63:0]  Address;
    reg [31:0] 	 Data;

    /*
    * ECEN 350 Processor Test Functions
    * Texas A&M University
    */

    always @ (Address) begin
        case(Address)
        /* Test Program 1:
         * Program loads constants from the data memory. Uses these constants to test
         * the following instructions: LDUR, ORR, AND, CBZ, ADD, SUB, STUR and B.
         *
         * Assembly code for test:
         *
         * 0x00: ORR  X20, XZR, XZR     //Create a base memory address
         * 0x04: LDUR X9,  [X20, 0x0]   //Load 1 into x9
         * 0x08: LDUR X10, [X20, 0x8]   //Load a into x10
         * 0x0c: LDUR X11, [X20, 0x10]  //Load 5 into x11
         * 0x10: LDUR X12, [X20, 0x18]  //Load big constant into x12
         * 0x14: LDUR X13, [X20, 0x20]  //load a 0 into X13
         *
         * 0x18: ORR X10, X10, X11  //Create mask of 0xf
         * 0x1c: AND X12, X12, X10  //Mask off low order bits of big constant
         *
         * loop:
         * 0x20: CBZ X12, end  //while X12 is not 0
         * 0x24: ADD X13, X13, X9  //Increment counter in X13
         * 0x28: SUB X12, X12, X9  //Decrement remainder of big constant in X12
         * 0x2c: B loop  //Repeat till X12 is 0
         * 0x30: STUR X13, [X20, 0x20]  //store back the counter value into the memory location 0x20
         * 0x34: LDUR X13, [X20, 0x20]  //One last load to place stored value on memdbus for test checking.
         */

        64'h000: Data = 32'hAA1F03F4;
        64'h004: Data = 32'hF8400289;
        64'h008: Data = 32'hF840828A;
        64'h00c: Data = 32'hF841028B;
        64'h010: Data = 32'hF841828C;
        64'h014: Data = 32'hF842028D;
        64'h018: Data = 32'hAA0B014A;
        64'h01c: Data = 32'h8A0A018C;
        64'h020: Data = 32'hB400008C;
        64'h024: Data = 32'h8B0901AD;
        64'h028: Data = 32'hCB09018C;
        64'h02c: Data = 32'h17FFFFFD;
        64'h030: Data = 32'hF802028D;
        64'h034: Data = 32'hF842028D;


        /* Add code for your tests here 
	* 0x38: MOVZ X9, #0xdef0 // LSL 0
	* 0x3C: MOVZ X10, #0x9abc // LSL 16
	* 0x40: ADD X11, X9, X10 //ORR X11, X9, X10 // X11 = 0x000009abcdef0
	* 0x44: MOVZ X9, #0x5678 // LSL 32
	* 0x48: MOVZ X10, #0x1234 // LSL 48
	* 0x4C: ADD X12, X9, X10 //ORR X12, X9, X19 // X12 = 0x1234567800000000
	* 0x50: ORR X9, X11, X12 // X9 = 0x123456789abcdef0
	* 0x54: ADD X0, XZR, XZR // X0 = 0
	* 0x58: STUR X9, [X0, #0x28] // X9->X0
	* 0x5C: LDUR X10, [X9, #0x28] // X10 = X9	
	*/

	64'h038: Data = 32'hD29BDE09;
        64'h03c: Data = 32'hD2B3578A;
        64'h040: Data = 32'h8B09014B;//AA09014B;
        64'h044: Data = 32'hD2CACF09;
        64'h048: Data = 32'hD2E2468A;
        64'h04c: Data = 32'h8B09014C;//AA09014A;
        64'h050: Data = 32'hAA0B0189;
        64'h054: Data = 32'h8B1F03E0;
        64'h058: Data = 32'hF8028009;
        64'h05c: Data = 32'hF842800A;
        
	// ADD = 10001011000
	// R-Format = {opcode[31:21], Rm[20:16], Shamt[15:10], Rn[9:5], Rd[4:0]}
	
//ADD X11, X9, X10 = 1000||1011||0000||1001||0000||0001||0100||1011 = 0x8B09014B
//ADD X12, X9, X10 = 1000||1011||0000||1001||0000||0001||0100||1100 = 0x8B09014C
//

        default: Data = 32'hXXXXXXXX;
        endcase
    end
endmodule

Lab09/nextpc.v
module NextPCLogic(
    output reg [63:0] NextPC,
    input      [63:0] CurrentPC,
    input      [63:0] SignExtImm64,
    input            Branch,
    input            ALUZero,
    input            Uncondbranch
);

always @(*)
begin


    if ((Uncondbranch) || (Branch && ALUZero))
          NextPC = (CurrentPC + (SignExtImm64 << 2));
     
    else 
          NextPC = CurrentPC + 4;
	
end

endmodule

Lab09/SingleCycleProcMOV.v
`include "alu.v"
`include "DataMemory.v"
`include "ImmGeneratorMOV.v"
`include "nextpc.v"
`include "InstructionMemory.v"
`include "registerfile.v"
`include "SingleCycleControlMOV.v"
`timescale 1ns / 1ps

module singlecycle(
    input resetl,
    input [63:0] startpc,
    output reg [63:0] currentpc,
    output [63:0] dmemout,
    input CLK
);

    // Next PC connections
    wire [63:0] nextpc;       // The next PC, to be updated on clock cycle

    // Instruction Memory connections
    wire [31:0] instruction;  // The current instruction

    // Parts of instruction
    wire [4:0] rd;            // The destination register
    wire [4:0] rm;            // Operand 1
    wire [4:0] rn;            // Operand 2
   // wire [5:0] shamt;
    wire [10:0] opcode;

   

    // Control wires
    wire reg2loc;
    wire alusrc;
    wire mem2reg;
    wire regwrite;
    wire memread;
    wire memwrite;
    wire branch;
    wire uncond_branch;
    wire [3:0] aluctrl;
    wire [2:0] signop;

    // Register file connections
    wire [63:0] regoutA;     // Output A
    wire [63:0] regoutB;     // Output B
    wire [63:0] reginW;	     // Input W

    // ALU connections
    wire [63:0] aluout;
    wire [63:0] aluin;
    wire zero;

    // Immediate generator connections
    wire [63:0] extimm; 
    wire [25:0] imm;


    NextPCLogic nextPC(.NextPC(nextpc),
		        .CurrentPC(currentpc),
			.SignExtImm64(extimm),
			.Branch(branch),
			.ALUZero(zero),
			.Uncondbranch(uncond_branch));
     InstructionMemory imem(
        .Data(instruction),
        .Address(currentpc)
    );

    // PC update logic
    always @(negedge CLK)
    begin
        if (~resetl)
            currentpc <= startpc;
        else
            currentpc <= nextpc;
    end

    // Parts of instruction
    assign rd = instruction[4:0];
    assign rn = instruction[9:5];
    assign rm = reg2loc ? instruction[4:0] : instruction[20:16];
    assign opcode = instruction[31:21];
    assign imm = instruction[25:0];

   

    SingleCycleControl control(
        .reg2loc(reg2loc),
        .alusrc(alusrc),
        .mem2reg(mem2reg),
        .regwrite(regwrite),
        .memread(memread),
        .memwrite(memwrite),
        .branch(branch),
        .uncond_branch(uncond_branch),
        .aluop(aluctrl),
        .signop(signop),
        .opcode(opcode)
    );

    /*
    * Connect the remaining datapath elements below.
    * Do not forget any additional multiplexers that may be required.
    */

	
    //REGISTER FILE
    RegisterFile registers(.BusA(regoutA), 
	.BusB(regoutB),
	.BusW(reginW),
	.RA(rn),
	.RB(rm),
	.RW(rd),
	.RegWr(regwrite),
	.Clk(CLK));
   	
	
    // IMMEDIATE GENERATOR
    ImmGenerator ImmGen(.Imm64(extimm), .Imm26(imm), .Ctrl(signop));
	
	
    // ALUSrc MUX
    assign aluin = alusrc ? extimm : regoutB; 
    
    // ALU
    alu ALU(.busW(aluout), 
	    .zero(zero),
	    .busA(regoutA),
	    .busB(aluin),
	    .ctrl(aluctrl));

    //DATA MEMORY
    DataMemory data(.ReadData(dmemout),
	  	    .Address(aluout),
		    .WriteData(regoutB),
		    .MemoryRead(memread),
		    .MemoryWrite(memwrite),
		    .Clock(CLK));

    // MemToReg MUX
    assign reginW = mem2reg ? dmemout : aluout;



endmodule

Lab09/SingleCycleProcTestMOV.v
`include "SingleCycleProcMOV.v"
`timescale 1ns / 1ps

`define STRLEN 32
`define HalfClockPeriod 60
`define ClockPeriod `HalfClockPeriod * 2

module SingleCycleProcTest_v;

    initial
    begin
        $dumpfile("singlecycle.vcd");
        $dumpvars;
    end

    // These tasks are used to check if a given test has passed and
    // confirm that all tests passed.
    task passTest;
        input [63:0] actualOut, expectedOut;
        input [`STRLEN*8:0] testType;
        inout [7:0] 	  passed;

        if(actualOut == expectedOut) begin $display ("%s passed", testType); passed = passed + 1; end
        else $display ("%s failed: 0x%x should be 0x%x", testType, actualOut, expectedOut);
    endtask

    task allPassed;
        input [7:0] passed;
        input [7:0] numTests;

        if(passed == numTests) $display ("All tests passed");
        else $display("Some tests failed: %d of %d passed", passed, numTests);
    endtask

    // Inputs
    reg        CLK;
    reg        Reset_L;
    reg [63:0] startPC;
    reg [7:0]  passed;
    reg [15:0] watchdog;

    // Outputs
    wire [63:0] dMemOut;
    wire [63:0] currentPC;

    // Instantiate the Unit Under Test (UUT)
    singlecycle uut (
        .CLK(CLK),
        .resetl(Reset_L),
        .startpc(startPC),
        .currentpc(currentPC),
        .dmemout(dMemOut)
    );

    initial begin
        // Initialize Inputs
        Reset_L = 1;
        startPC = 0;
        passed = 0;

        // Initialize Watchdog timer
        watchdog = 0;

        // Wait for global reset
        #(1 * `ClockPeriod);

        // Program 1
        #1
        Reset_L = 0; startPC = 0;
        #(1 * `ClockPeriod);
        Reset_L = 1;

        // ***********************************************************
        // This while loop will continue cycling the processor until the
        // PC reaches the final instruction in the first test.  If the
        // program forms an infinite loop, never reaching the end, the
        // watchdog timer will kick in and kill simulation after 64K
        // cycles.
        // ***********************************************************

        while (currentPC < 64'h34)
        begin
           #(1 * `ClockPeriod);
           $display("CurrentPC:%h",currentPC);
        end
        #(1 * `ClockPeriod);	// One more cycle to load the pass code from the DataMemory.
        passTest(dMemOut, 64'hF, "Results of Program 1", passed);

        // ***********************************************************
        // Add your new tests here
        // ***********************************************************

        // Done
        allPassed(passed, 2);   // Be sure to change the one to match
                                // the number of tests you add.
        $finish;
    end

    initial begin
        CLK = 0;
    end

    // The following is correct if clock starts at LOW level at StartTime //
    always begin
        #`HalfClockPeriod CLK = ~CLK;
        #`HalfClockPeriod CLK = ~CLK;
        watchdog = watchdog +1;
    end

    // Kill the simulation if the watchdog hits 64K cycles
    always @*
        if (watchdog == 16'hFF)
        begin
            $display("Watchdog Timer Expired.");
            $finish;
        end


endmodule

Lab09/singlecycle.vcd
$date
	Thu Apr 23 10:21:56 2020
$end

$version
	Synopsys VCS version L-2016.06-SP2-4_Full64
$end

$timescale
	1ps
$end

$comment Csum: 1 dd709ed0f0839fe3 $end


$scope module SingleCycleProcTest_v $end
$var reg 1 ! CLK $end
$var reg 1 " Reset_L $end
$var reg 64 # startPC [63:0] $end
$var reg 8 $ passed [7:0] $end
$var reg 16 % watchdog [15:0] $end
$var wire 64 & dMemOut [63:0] $end
$var wire 64 ' currentPC [63:0] $end

$scope task passTest $end
$var reg 64 ( actualOut [63:0] $end
$var reg 64 ) expectedOut [63:0] $end
$var reg 257 * testType [256:0] $end
$var reg 8 + passed [7:0] $end
$upscope $end


$scope task allPassed $end
$var reg 8 , passed [7:0] $end
$var reg 8 - numTests [7:0] $end
$upscope $end


$scope module uut $end
$var wire 1 " resetl $end
$var wire 64 # startpc [63:0] $end
$var reg 64 ' currentpc [63:0] $end
$var wire 64 & dmemout [63:0] $end
$var wire 1 ! CLK $end
$var wire 64 . nextpc [63:0] $end
$var wire 32 / instruction [31:0] $end
$var wire 5 0 rd [4:0] $end
$var wire 5 1 rm [4:0] $end
$var wire 5 2 rn [4:0] $end
$var wire 11 3 opcode [10:0] $end
$var wire 1 4 reg2loc $end
$var wire 1 5 alusrc $end
$var wire 1 6 mem2reg $end
$var wire 1 7 regwrite $end
$var wire 1 8 memread $end
$var wire 1 9 memwrite $end
$var wire 1 : branch $end
$var wire 1 ; uncond_branch $end
$var wire 4 < aluctrl [3:0] $end
$var wire 3 = signop [2:0] $end
$var wire 64 > regoutA [63:0] $end
$var wire 64 ? regoutB [63:0] $end
$var wire 64 @ reginW [63:0] $end
$var wire 64 A aluout [63:0] $end
$var wire 64 B aluin [63:0] $end
$var wire 1 C zero $end
$var wire 64 D extimm [63:0] $end
$var wire 26 E imm [25:0] $end

$scope module nextPC $end
$var reg 64 . NextPC [63:0] $end
$var wire 64 ' CurrentPC [63:0] $end
$var wire 64 D SignExtImm64 [63:0] $end
$var wire 1 : Branch $end
$var wire 1 C ALUZero $end
$var wire 1 ; Uncondbranch $end
$upscope $end


$scope module imem $end
$var reg 32 / Data [31:0] $end
$var wire 64 ' Address [63:0] $end
$upscope $end


$scope module control $end
$var reg 1 4 reg2loc $end
$var reg 1 5 alusrc $end
$var reg 1 6 mem2reg $end
$var reg 1 7 regwrite $end
$var reg 1 8 memread $end
$var reg 1 9 memwrite $end
$var reg 1 : branch $end
$var reg 1 ; uncond_branch $end
$var reg 4 < aluop [3:0] $end
$var reg 3 = signop [2:0] $end
$var wire 11 F opcode [10:0] $end
$upscope $end


$scope module registers $end
$var wire 64 > BusA [63:0] $end
$var wire 64 ? BusB [63:0] $end
$var wire 64 @ BusW [63:0] $end
$var wire 5 2 RA [4:0] $end
$var wire 5 1 RB [4:0] $end
$var wire 5 0 RW [4:0] $end
$var wire 1 7 RegWr $end
$var wire 1 ! Clk $end
$upscope $end


$scope module ImmGen $end
$var reg 64 D Imm64 [63:0] $end
$var wire 26 G Imm26 [25:0] $end
$var wire 3 = Ctrl [2:0] $end
$var wire 1 H extBit $end
$upscope $end


$scope module ALU $end
$var wire 64 A busW [63:0] $end
$var wire 1 C zero $end
$var wire 64 > busA [63:0] $end
$var wire 64 B busB [63:0] $end
$var wire 4 < ctrl [3:0] $end
$upscope $end


$scope module data $end
$var wire 64 ? WriteData [63:0] $end
$var wire 64 A Address [63:0] $end
$var wire 1 ! Clock $end
$var wire 1 8 MemoryRead $end
$var wire 1 9 MemoryWrite $end
$var reg 64 & ReadData [63:0] $end

$scope task initset $end
$var reg 64 I addr [63:0] $end
$var reg 64 J data [63:0] $end
$upscope $end

$upscope $end

$upscope $end

$upscope $end

$enddefinitions $end

#0
$dumpvars
0!
1"
x5
x:
x6
x8
x9
x4
x7
x;
zH
xC
bxxxxxxxxxxxxxxxxxxxxxxxxxxxxxxxx /
bxxxxxxxxxxxxxxxxxxxxxxxxxx G
bxxxxxxxxxxxxxxxxxxxxxxxxxxxxxxxxxxxxxxxxxxxxxxxxxxxxxxxxxxxxxxxx D
bxxxxxxxxxxxxxxxxxxxxxxxxxxxxxxxxxxxxxxxxxxxxxxxxxxxxxxxxxxxxxxxx .
bxxxxxxxxxxxxxxxxxxxxxxxxxxxxxxxxxxxxxxxxxxxxxxxxxxxxxxxxxxxxxxxx &
bxxxxxxxx -
bxxxxxxxx ,
bxxxxxxxxxxxxxxxxxxxxxxxxxxxxxxxxxxxxxxxxxxxxxxxxxxxxxxxxxxxxxxxx B
bxxxx <
bxxxxxxxxxxxxxxxxxxxxxxxxxxxxxxxxxxxxxxxxxxxxxxxxxxxxxxxxxxxxxxxx A
bxxxxxxxxxxx F
bxxx =
bxxxxxxxxxxxxxxxxxxxxxxxxxxxxxxxxxxxxxxxxxxxxxxxxxxxxxxxxxxxxxxxx '
b0000000000000000000000000000000000000000000000000000000000100000 I
b0000000000000000000000000000000000000000000000000000000000000000 J
bxxxxxxxxxxxxxxxxxxxxxxxxxxxxxxxxxxxxxxxxxxxxxxxxxxxxxxxxxxxxxxxx (
bxxxxxxxxxxxxxxxxxxxxxxxxxxxxxxxxxxxxxxxxxxxxxxxxxxxxxxxxxxxxxxxx )
bxxxxxxxx +
bxxxxxxxxxxxxxxxxxxxxxxxxxxxxxxxxxxxxxxxxxxxxxxxxxxxxxxxxxxxxxxxxxxxxxxxxxxxxxxxxxxxxxxxxxxxxxxxxxxxxxxxxxxxxxxxxxxxxxxxxxxxxxxxxxxxxxxxxxxxxxxxxxxxxxxxxxxxxxxxxxxxxxxxxxxxxxxxxxxxxxxxxxxxxxxxxxxxxxxxxxxxxxxxxxxxxxxxxxxxxxxxxxxxxxxxxxxxxxxxxxxxxxxxxxxxxxxxxx *
b00000000 $
bxxxxxxxxxxxxxxxxxxxxxxxxxxxxxxxxxxxxxxxxxxxxxxxxxxxxxxxxxxxxxxxx @
bxxxxxxxxxxxxxxxxxxxxxxxxxxxxxxxxxxxxxxxxxxxxxxxxxxxxxxxxxxxxxxxx >
bxxxxxxxxxxxxxxxxxxxxxxxxxxxxxxxxxxxxxxxxxxxxxxxxxxxxxxxxxxxxxxxx ?
bxxxxx 1
b0000000000000000000000000000000000000000000000000000000000000000 #
bxxxxx 2
bxxxxx 0
bxxxxxxxxxxx 3
bxxxxxxxxxxxxxxxxxxxxxxxxxx E
b0000000000000000 %
$end
#60000
1!
#120000
0!
b0000000000000001 %
#121000
0"
#180000
1!
#240000
0!
b0000000000000010 %
b0000000000000000000000000000000000000000000000000000000000000000 '
b0000000000000000000000000000000000000000000000000000000000000100 .
b10101010000111110000001111110100 /
b10100 0
b11111 2
b10101010000 3
b10000111110000001111110100 E
b10101010000 F
b10000111110000001111110100 G
b0000000000000000000000000000000000000000000000000000000000000000 >
b1x1xx 1
04
05
17
08
09
0:
0;
b0001 <
06
b11111 1
b0000000000000000000000000000000000000000000000000000000000000000 ?
b0000000000000000000000000000000000000000000000000000000000000000 B
b0000000000000000000000000000000000000000000000000000000000000000 A
1C
b0000000000000000000000000000000000000000000000000000000000000000 @
#241000
1"
#300000
1!
#360000
0!
b0000000000000011 %
b0000000000000000000000000000000000000000000000000000000000000100 '
b0000000000000000000000000000000000000000000000000000000000001000 .
b11111000010000000000001010001001 /
b01001 0
b10100 2
b11111000010 3
b00010000000000001010001001 E
b11111000010 F
b00010000000000001010001001 G
b00000 1
bxxxxxxxxxxxxxxxxxxxxxxxxxxxxxxxxxxxxxxxxxxxxxxxxxxxxxxxxxxxxxxxx ?
bxxxxxxxxxxxxxxxxxxxxxxxxxxxxxxxxxxxxxxxxxxxxxxxxxxxxxxxxxxxxxxxx B
bxxxxxxxxxxxxxxxxxxxxxxxxxxxxxxxxxxxxxxxxxxxxxxxxxxxxxxxxxxxxxxxx A
xC
bxxxxxxxxxxxxxxxxxxxxxxxxxxxxxxxxxxxxxxxxxxxxxxxxxxxxxxxxxxxxxxxx @
x4
15
18
b0010 <
b001 =
16
b0x00x 1
b0000000000000000000000000000000000000000000000000000000000000000 D
b0000000000000000000000000000000000000000000000000000000000000000 B
b0000000000000000000000000000000000000000000000000000000000000000 A
1C
#420000
1!
#440000
b0000000000000000000000000000000000000000000000000000000000000001 &
b0000000000000000000000000000000000000000000000000000000000000001 @
#480000
0!
b0000000000000100 %
b0000000000000000000000000000000000000000000000000000000000001000 '
b0000000000000000000000000000000000000000000000000000000000001100 .
b11111000010000001000001010001010 /
b01010 0
b00010000001000001010001010 E
b00010000001000001010001010 G
b0x0x0 1
b0000000000000000000000000000000000000000000000000000000000001000 D
b0000000000000000000000000000000000000000000000000000000000001000 B
b0000000000000000000000000000000000000000000000000000000000001000 A
0C
#540000
1!
#560000
b0000000000000000000000000000000000000000000000000000000000001010 &
b0000000000000000000000000000000000000000000000000000000000001010 @
#600000
0!
b0000000000000101 %
b0000000000000000000000000000000000000000000000000000000000001100 '
b0000000000000000000000000000000000000000000000000000000000010000 .
b11111000010000010000001010001011 /
b01011 0
b00010000010000001010001011 E
b00010000010000001010001011 G
b0x0x1 1
b0000000000000000000000000000000000000000000000000000000000010000 D
b0000000000000000000000000000000000000000000000000000000000010000 B
b0000000000000000000000000000000000000000000000000000000000010000 A
#660000
1!
#680000
b0000000000000000000000000000000000000000000000000000000000000101 &
b0000000000000000000000000000000000000000000000000000000000000101 @
#720000
0!
b0000000000000110 %
b0000000000000000000000000000000000000000000000000000000000010000 '
b0000000000000000000000000000000000000000000000000000000000010100 .
b11111000010000011000001010001100 /
b01100 0
b00010000011000001010001100 E
b00010000011000001010001100 G
b0xx0x 1
b0000000000000000000000000000000000000000000000000000000000011000 D
b0000000000000000000000000000000000000000000000000000000000011000 B
b0000000000000000000000000000000000000000000000000000000000011000 A
#780000
1!
